wizard101/__init__.py
wizard101/petgames.py
wizard101/util.py
auto_wizard101-1.0.4.dist-info/LICENSE
auto_wizard101-1.0.4.dist-info/METADATA
auto_wizard101-1.0.4.dist-info/WHEEL
auto_wizard101-1.0.4.dist-info/top_level.txt
auto_wizard101-1.0.4.dist-info/RECORD
