Metadata-Version: 2.1
Name: auto-wizard101
Version: 1.0.4
Summary: Automatically complete repetitive tasks in wizard101.
Home-page: https://github.com/GabeMillikan/auto-wizard101
Author: gabemillikan
License: UNKNOWN
Project-URL: Bug Tracker, https://github.com/GabeMillikan/auto-wizard101/issues
Platform: UNKNOWN
Classifier: Programming Language :: Python :: 3
Classifier: License :: OSI Approved :: GNU General Public License v3 (GPLv3)
Classifier: Operating System :: OS Independent
Requires-Python: >=3.6
License-File: LICENSE
Requires-Dist: opencv-python
Requires-Dist: keyboard
Requires-Dist: mss
